fastapi_hive/__init__.py
fastapi_hive/ioc_framework/__init__.py
fastapi_hive/ioc_framework/di_contiainer.py
fastapi_hive/ioc_framework/implement.py
fastapi_hive/ioc_framework/ioc_config.py
fastapi_hive/ioc_framework/module_abstraction/__init__.py
fastapi_hive/ioc_framework/module_abstraction/module.py
fastapi_hive/ioc_framework/module_container/__init__.py
fastapi_hive/ioc_framework/module_container/implement.py
fastapi_hive/ioc_framework/module_container/module_path.py
fastapi_hive/ioc_framework/module_mounter/__init__.py
fastapi_hive/ioc_framework/module_mounter/implement.py
fastapi_hive/ioc_framework/router_mounter/__init__.py
fastapi_hive/ioc_framework/router_mounter/implement.py
fastapi_hive-1.0.8.dist-info/LICENSE
fastapi_hive-1.0.8.dist-info/METADATA
fastapi_hive-1.0.8.dist-info/WHEEL
fastapi_hive-1.0.8.dist-info/top_level.txt
fastapi_hive-1.0.8.dist-info/RECORD
