Metadata-Version: 2.1
Name: fastapi-hive
Version: 1.0.8
Summary: framework for FastAPI modules management
Home-page: https://github.com/fanqingsong/fastapi-hive
Author: Qingsong Fan
Author-email: qsfan@qq.com
License: Apache-2.0 license
Project-URL: Issue Tracker, https://github.com/fanqingsong/fastapi-hive/issues
Project-URL: Documentation, https://fanqingsong.github.io/fastapi-hive/
Keywords: fastapi machine-learning packages modules
Classifier: Development Status :: 5 - Production/Stable
Classifier: Intended Audience :: Developers
Classifier: Topic :: Software Development :: Libraries :: Application Frameworks
Classifier: Topic :: Software Development :: Libraries :: Python Modules
Classifier: Topic :: Software Development :: Libraries
Classifier: Topic :: Software Development
Classifier: Topic :: Internet :: WWW/HTTP :: WSGI :: Application
Classifier: License :: OSI Approved :: Apache Software License
Classifier: Operating System :: OS Independent
Classifier: Programming Language :: Python :: 3 :: Only
Classifier: Programming Language :: Python :: 3.7
Classifier: Programming Language :: Python :: 3.8
Requires-Python: >=3.7
License-File: LICENSE
Requires-Dist: fastapi (>=0.48.0)
Requires-Dist: loguru (>=0.4.1)
Requires-Dist: dependency-injector (>=4.40.0)
